multiroutes/__init__.py
multiroutes/multiroutes.py
multiroutes-0.1.dist-info/METADATA
multiroutes-0.1.dist-info/WHEEL
multiroutes-0.1.dist-info/top_level.txt
multiroutes-0.1.dist-info/RECORD
