Metadata-Version: 2.1
Name: multiroutes
Version: 0.1
Summary: A simple Flask route manager library.
Author: Seu Nome
Author-email: seu.email@example.com
Classifier: Programming Language :: Python :: 3
Classifier: License :: OSI Approved :: MIT License
Classifier: Operating System :: OS Independent
Requires-Python: >=3.6
Requires-Dist: Flask
